{
  "updated_at": "2026-07-06T21:30+07:00",
  "session": "21:30",
  "future": 4148.4,
  "spot_cfd": 4129.4,
  "basis": 19.0,
  "basis_live": false,
  "regime": "normal",
  "sigma": 20.8,
  "atm_iv": 26.56,
  "dte": 0.13,
  "bias": "long",
  "headline": "ทองขึ้น +22.7 มาที่ 4148.4 · IV 26.56% (regime normal) · P/C OI 0.79 · skew สมดุล (Put 18.9% vs Call 18.5%). มอง LONG (โมเมนตัมขึ้น) — รอย่อหาแนวรับ 4115 แล้วค่อยหาจังหวะ อย่าไล่",
  "resistance": [
    {
      "price": 4150,
      "cfd": 4131.0,
      "note": "กำแพง Call · ≈ราคาปัจจุบัน"
    },
    {
      "price": 4200,
      "cfd": 4181.0,
      "note": "Magnet (OI หนาสุด) · ท้าย OI Call = เป้าบนสุด · ยืนยัน 2 จอ · +2σ"
    }
  ],
  "support": [
    {
      "price": 4115,
      "cfd": 4096.0,
      "note": "กำแพง Put · −2σ"
    },
    {
      "price": 4100,
      "cfd": 4081.0,
      "note": "ท้าย OI Put = แนวรับสุดท้าย · ยืนยัน 2 จอ · −2σ"
    }
  ],
  "scenarios": [
    "ย่อลงหาแนวรับ 4115 แล้วเกิดไส้เทียน H1 reject (ทิ้งไส้ล่าง) → long ตามเทรนด์ขึ้น เป้า 4150 → 4169 (+1σ)",
    "ทะลุ 4150 + วอลุ่ม/OI ฝั่งขึ้นเพิ่ม (Gamma squeeze ของจริง ห้ามสวน) → ไปต่อหา 4200 (ท้าย OI)",
    "กลับตัวลงเฉพาะครบเงื่อนไข: ราคาแตะ 4200 + IV หักหัวลง + ไส้เทียน H1 → short สั้นสวน (เสี่ยงสูง)"
  ],
  "entries": [
    {
      "side": "long",
      "title": "Long รีเจกต์แนวรับ",
      "entry": 4096.0,
      "sl": 4084.0,
      "tp": [
        4131.0,
        4181.0
      ],
      "rr": "≈1:2.9",
      "note": "รอย่อลง 4096.0 (fut 4115) + ไส้เทียน H1 reject (ทิ้งไส้ล่าง) แล้วค่อย Long"
    },
    {
      "side": "long",
      "title": "Long ตามการทะลุ",
      "entry": 4131.0,
      "sl": 4119.0,
      "tp": [
        4181.0
      ],
      "rr": "≈1:4.2",
      "note": "ถ้าปิด H1 เหนือ 4131.0 (fut 4150) + วอลุ่ม/OI ฝั่งขึ้นเพิ่ม (Gamma squeeze)"
    }
  ],
  "grid": [
    {
      "price": 3950,
      "cfd": 3931.0,
      "r100": false,
      "oi": false
    },
    {
      "price": 4000,
      "cfd": 3981.0,
      "r100": true,
      "oi": false
    },
    {
      "price": 4050,
      "cfd": 4031.0,
      "r100": false,
      "oi": false
    },
    {
      "price": 4100,
      "cfd": 4081.0,
      "r100": true,
      "oi": true
    },
    {
      "price": 4150,
      "cfd": 4131.0,
      "r100": false,
      "oi": true
    },
    {
      "price": 4200,
      "cfd": 4181.0,
      "r100": true,
      "oi": true
    },
    {
      "price": 4250,
      "cfd": 4231.0,
      "r100": false,
      "oi": false
    }
  ],
  "cot": {
    "date": "2026-06-23",
    "comm": {
      "net": -205404,
      "chg": 2159
    },
    "spec": {
      "net": 181339,
      "chg": 1119
    },
    "retail": {
      "net": 24065,
      "chg": -3278
    },
    "retail_lean": "flat"
  },
  "risk": "ผันผวนปกติ → เทรดตามแนว OI ได้ แต่ยังต้องรอจังหวะยืนยัน; ทองลงแรงกว่าขึ้น + fat tails → RR ต้องเป็นบวก อย่าเติมไม้ตอนแพง; รอไส้เทียน H1/H4 ยืนยันก่อนเข้า วาง SL หลังไส้/หลังกำแพง OI · RR ≥ 1:2; ใกล้หมดอายุ (DTE 0.13) → กำแพง OI บาง/แกว่งแรงช่วงหมดอายุ; จุดเข้า/SL/TP + แนวรับต้าน = ราคา CFD/XAUUSD (แปลงจาก futures ด้วย basis −19 ประมาณ); basis ขยับตามตลาด ควรเทียบกับราคาโบรกฯ ของคุณอีกที; $50 Grid (Block Trade): ต้านใกล้สุด 4150 (CFD 4131.0 ★OI) / รับใกล้สุด 4100 (CFD 4081.0 ★OI) — ทุกระดับ $50/$100 = ด่าน MM hedge; COT 2026-06-23 (CFTC รายสัปดาห์): รายย่อย net +24,065 ยังไม่สุดขั้ว → แทบไม่มีน้ำหนัก (รอราคายืนยัน) · กองทุน(specs) net +181,339 · Smart money(comm) net -205,404 (comm+spec = แกนเดียว กระจกกัน)",
  "source": "The Invisible Money + OI มีอยู่จริง + OI/Vol (CME)",
  "oi_change": {
    "vs_date": "2026-07-03",
    "contract_changed": true,
    "top": []
  }
}